cookie/__init__.py
cookie/api.py
cookie/errors.py
cookie/models.py
cookie/_internal/__init__.py
cookie/_internal/custom_models.py
cookie/_internal/formatter.py
cookie/_internal/model_generator.py
cookie_api-0.3.0.dist-info/licenses/LICENSE
cookie_api-0.3.0.dist-info/METADATA
cookie_api-0.3.0.dist-info/WHEEL
cookie_api-0.3.0.dist-info/top_level.txt
cookie_api-0.3.0.dist-info/RECORD
