Metadata-Version: 2.4
Name: cookie-api
Version: 0.3.0
Summary: An API wrapper for the Cookie API
Author: tibue99, tobfd
License: MIT
Project-URL: GitHub, https://github.com/tibue99/cookie-api
Project-URL: Cookie, https://cookieapp.me
Project-URL: Documentation, https://cookie-api.readthedocs.io
Project-URL: OpenAPI, https://api.cookieapp.me/docs
Keywords: discord,bot,cookie,api
Classifier: Development Status :: 5 - Production/Stable
Classifier: License :: OSI Approved :: MIT License
Classifier: Intended Audience :: Developers
Classifier: Operating System :: OS Independent
Classifier: Programming Language :: Python :: 3.9
Classifier: Programming Language :: Python :: 3.10
Classifier: Programming Language :: Python :: 3.11
Classifier: Programming Language :: Python :: 3.12
Classifier: Programming Language :: Python :: 3.13
Requires-Python: >=3.9
License-File: LICENSE
Requires-Dist: httpx
Requires-Dist: pydantic
Requires-Dist: python-dotenv
Requires-Dist: eval_type_backport; python_version <= "3.9"
Dynamic: license-file
